dbscan.py
pyspark_dbscan-1.0.6.dist-info/METADATA
pyspark_dbscan-1.0.6.dist-info/WHEEL
pyspark_dbscan-1.0.6.dist-info/top_level.txt
pyspark_dbscan-1.0.6.dist-info/RECORD
