Metadata-Version: 2.1
Name: pyspark-dbscan
Version: 1.0.6
Summary: An "Efficient" Implementation of DBSCAN on PySpark
Requires-Python: >=3.6
Requires-Dist: numpy (>=1.19.0)
Requires-Dist: pyspark (>=3.1.0)
Requires-Dist: scipy (>=1.5.4)
Requires-Dist: sklearn (==0.0)
Requires-Dist: scikit-learn (==0.24.2)
Requires-Dist: graphframes (==0.6)
